Workbook

Sheet COCKPIT
C1: 🏢 COCKPIT DE PILOTAGE TRÉSORERIE · CSE LIDL ENTZHEIM · Exercice Mars 2026 – Février 2027
C2: Suivi budgétaire mensuel | Mise à jour : Juin 2026 | Données source : Pennylane
C4: 💰 Trésorerie actuelle | E4: 📈 Projection fin exercice | G4: 📋 Budget total annuel | I4: ✅ Réalisé cumulé dépenses | K4: ⏳ Reste à consommer | M4: 📅 Mois réalisés
C5: 470 450 € | E5: 458 455 € | G5: 13 000 € | I5: 47 783 € | K5: 0 € | M5: 3 / 12
C6: Fin mai 2026 (dernier réalisé) | E6: Feb 2027 (Pennylane) | G6: Saisir le budget complet → | I6: Mars → Juin 2026 | K6: À compléter après saisie budget | M6: Mars, Avril, Mai 2026
C9: 📊 SYNTHÈSE PAR CATÉGORIE — Budget vs Réalisé (Exercice Mars 2026 – Février 2027)
C10: CATÉGORIE | E10: BUDGET N | F10: RÉALISÉ CUM. | G10: ÉCART € | H10: % EXEC | I10: STATUT | K10: MOIS ACTIF | L10: TENDANCE
C11: ENTRÉES | E11: ='PLAN TRÉSO'!D5 | F11: ='PLAN TRÉSO'!E5 | G11: ='PLAN TRÉSO'!E5-'PLAN TRÉSO'!D5 | H11: ='PLAN TRÉSO'!H5 | I11: ='PLAN TRÉSO'!I5 | K11: =(RÉALISÉ!D5<>0)+(RÉALISÉ!E5<>0)+(RÉALISÉ!F5<>0)+(RÉALISÉ!G5<>0) | L11: (graphique)
C12: Recette de la billetterie | E12: ='PLAN TRÉSO'!D6 | F12: ='PLAN TRÉSO'!E6 | G12: ='PLAN TRÉSO'!E6-'PLAN TRÉSO'!D6 | H12: ='PLAN TRÉSO'!H6 | I12: ='PLAN TRÉSO'!I6 | K12: =(RÉALISÉ!D6<>0)+(RÉALISÉ!E6<>0)+(RÉALISÉ!F6<>0)+(RÉALISÉ!G6<>0) | L12: (graphique)
C13: SORTIES | E13: ='PLAN TRÉSO'!D11 | F13: ='PLAN TRÉSO'!E11 | G13: ='PLAN TRÉSO'!E11-'PLAN TRÉSO'!D11 | H13: ='PLAN TRÉSO'!H11 | I13: ='PLAN TRÉSO'!I11 | K13: =(RÉALISÉ!D11<>0)+(RÉALISÉ!E11<>0)+(RÉALISÉ!F11<>0)+(RÉALISÉ!G11<>0) | L13: (graphique)
C14: Achat Billets | E14: ='PLAN TRÉSO'!D12 | F14: ='PLAN TRÉSO'!E12 | G14: ='PLAN TRÉSO'!E12-'PLAN TRÉSO'!D12 | H14: ='PLAN TRÉSO'!H12 | I14: ='PLAN TRÉSO'!I12 | K14: =(RÉALISÉ!D12<>0)+(RÉALISÉ!E12<>0)+(RÉALISÉ!F12<>0)+(RÉALISÉ!G12<>0) | L14: (graphique)
C15: Activités de loisirs | E15: ='PLAN TRÉSO'!D29 | F15: ='PLAN TRÉSO'!E29 | G15: ='PLAN TRÉSO'!E29-'PLAN TRÉSO'!D29 | H15: ='PLAN TRÉSO'!H29 | I15: ='PLAN TRÉSO'!I29 | K15: =(RÉALISÉ!D29<>0)+(RÉALISÉ!E29<>0)+(RÉALISÉ!F29<>0)+(RÉALISÉ!G29<>0) | L15: (graphique)
C16: Aides aux voyages | E16: ='PLAN TRÉSO'!D31 | F16: ='PLAN TRÉSO'!E31 | G16: ='PLAN TRÉSO'!E31-'PLAN TRÉSO'!D31 | H16: ='PLAN TRÉSO'!H31 | I16: ='PLAN TRÉSO'!I31 | K16: =(RÉALISÉ!D31<>0)+(RÉALISÉ!E31<>0)+(RÉALISÉ!F31<>0)+(RÉALISÉ!G31<>0) | L16: (graphique)
C17: Frais bancaires | E17: ='PLAN TRÉSO'!D42 | F17: ='PLAN TRÉSO'!E42 | G17: ='PLAN TRÉSO'!E42-'PLAN TRÉSO'!D42 | H17: ='PLAN TRÉSO'!H42 | I17: ='PLAN TRÉSO'!I42 | K17: =(RÉALISÉ!D42<>0)+(RÉALISÉ!E42<>0)+(RÉALISÉ!F42<>0)+(RÉALISÉ!G42<>0) | L17: (graphique)
C18: Téléphone & Internet | E18: ='PLAN TRÉSO'!D54 | F18: ='PLAN TRÉSO'!E54 | G18: ='PLAN TRÉSO'!E54-'PLAN TRÉSO'!D54 | H18: ='PLAN TRÉSO'!H54 | I18: ='PLAN TRÉSO'!I54 | K18: =(RÉALISÉ!D54<>0)+(RÉALISÉ!E54<>0)+(RÉALISÉ!F54<>0)+(RÉALISÉ!G54<>0) | L18: (graphique)
C19: Sorties non catégorisées | E19: ='PLAN TRÉSO'!D58 | F19: ='PLAN TRÉSO'!E58 | G19: ='PLAN TRÉSO'!E58-'PLAN TRÉSO'!D58 | H19: ='PLAN TRÉSO'!H58 | I19: ='PLAN TRÉSO'!I58 | K19: =(RÉALISÉ!D58<>0)+(RÉALISÉ!E58<>0)+(RÉALISÉ!F58<>0)+(RÉALISÉ!G58<>0) | L19: (graphique)
C20: Bureaux | E20: ='PLAN TRÉSO'!D35 | F20: ='PLAN TRÉSO'!E35 | G20: ='PLAN TRÉSO'!E35-'PLAN TRÉSO'!D35 | H20: ='PLAN TRÉSO'!H35 | I20: ='PLAN TRÉSO'!I35 | K20: =(RÉALISÉ!D35<>0)+(RÉALISÉ!E35<>0)+(RÉALISÉ!F35<>0)+(RÉALISÉ!G35<>0) | L20: (graphique)
C21: Restauration | E21: ='PLAN TRÉSO'!D49 | F21: ='PLAN TRÉSO'!E49 | G21: ='PLAN TRÉSO'!E49-'PLAN TRÉSO'!D49 | H21: ='PLAN TRÉSO'!H49 | I21: ='PLAN TRÉSO'!I49 | K21: =(RÉALISÉ!D49<>0)+(RÉALISÉ!E49<>0)+(RÉALISÉ!F49<>0)+(RÉALISÉ!G49<>0) | L21: (graphique)
C22: Sous-traitance & Prestations | E22: ='PLAN TRÉSO'!D52 | F22: ='PLAN TRÉSO'!E52 | G22: ='PLAN TRÉSO'!E52-'PLAN TRÉSO'!D52 | H22: ='PLAN TRÉSO'!H52 | I22: ='PLAN TRÉSO'!I52 | K22: =(RÉALISÉ!D52<>0)+(RÉALISÉ!E52<>0)+(RÉALISÉ!F52<>0)+(RÉALISÉ!G52<>0) | L22: (graphique)
C23: Déplacements | E23: ='PLAN TRÉSO'!D40 | F23: ='PLAN TRÉSO'!E40 | G23: ='PLAN TRÉSO'!E40-'PLAN TRÉSO'!D40 | H23: ='PLAN TRÉSO'!H40 | I23: ='PLAN TRÉSO'!I40 | K23: =(RÉALISÉ!D40<>0)+(RÉALISÉ!E40<>0)+(RÉALISÉ!F40<>0)+(RÉALISÉ!G40<>0) | L23: (graphique)
C25: 💹 ÉVOLUTION DE LA TRÉSORERIE MENSUELLE
C26: MOIS | D26: Mar.26 | E26: Avr.26 | F26: Mai.26 | G26: Jun.26 | H26: Jul.26 | I26: Aoû.26 | J26: Sep.26 | K26: Oct.26 | L26: Nov.26 | M26: Déc.26
C27: Trésorerie fin de mois | D27: =RÉALISÉ!D60 | E27: =RÉALISÉ!E60 | F27: =RÉALISÉ!F60 | G27: =RÉALISÉ!G60 | H27: =RÉALISÉ!H60 | I27: =RÉALISÉ!I60 | J27: =RÉALISÉ!J60 | K27: =RÉALISÉ!K60 | ... M27: =RÉALISÉ!M60
C28: Entrées | D28: =RÉALISÉ!D5 | E28: =RÉALISÉ!E5 | F28: =RÉALISÉ!F5 | G28: =RÉALISÉ!G5 | H28: =RÉALISÉ!H5 | I28: =RÉALISÉ!I5 | J28: =RÉALISÉ!J5 | K28: =RÉALISÉ!K5 | ... M28: =RÉALISÉ!M5
C29: Sorties | D29: =RÉALISÉ!D11 | E29: =RÉALISÉ!E11 | F29: =RÉALISÉ!F11 | G29: =RÉALISÉ!G11 | H29: =RÉALISÉ!H11 | I29: =RÉALISÉ!I11 | J29: =RÉALISÉ!J11 | K29: =RÉALISÉ!K11 | ... M29: =RÉALISÉ!M11
C31: ⚠️ ALERTES AUTOMATIQUES
C32: 🔵 Budget en cours de saisie — veuillez renseigner l'onglet BUDGET pour activer les alertes budgétaires.
C33: 🟡 | D33: Sorties non catégorisées très élevées : 59 097 € cumulés sur Mars–Juin 2026 → Vérifier la ventilation analytique dans Pennylane
C34: 🟡 | D34: Achat Billets : solde net négatif (-31 339 €) → Normal si avances remboursées, à surveiller
C35: 🟢 | D35: Frais bancaires : 307 € cumulés → Niveau normal pour un CSE
C36: 🔵 | D36: Budget à saisir pour 9 catégories sans prévision → Risque de dépassement non détecté
C38: Outil conçu avec Claude Code · Expert-comptable CSE · Données Pennylane · Mars 2026 – Février 2027

Sheet PLAN TRÉSO
C1: 📊 PLAN DE TRÉSORERIE — Réalisé vs Budget | CSE LIDL ENTZHEIM | Mars 2026 – Février 2027
C2: CATÉGORIE | D2: ◀ SYNTHÈSE ANNUELLE ▶ | J2: Mars 2026 | M2: Avril 2026 | P2: Mai 2026 | S2: Juin 2026 | V2: Juillet 2026 | Y2: Août 2026 | AB2: Septembre 2026 | AE2: Octobre 2026 | AH2: Novembre 2026 | AK2: Décembre 2026 | AN2: Janvier 2027 | AQ2: Février 2027
D3: Budget N | E3: Réalisé | F3: À venir | G3: Reste | H3: % Exec | I3: Statut | J3: Budget | K3: Réalisé | L3: Écart | M3: Budget | N3: Réalisé | O3: Écart | P3: Budget | Q3: Réalisé | R3: Écart | S3: Budget | T3: Réalisé | U3: Écart | V3: Budget | W3: Réalisé | X3: Écart | Y3: Budget | Z3: Réalisé | AA3: Écart | AB3: Budget | AC3: Réalisé | AD3: Écart | AE3: Budget | AF3: Réalisé | AG3: Écart | AH3: Budget | AI3: Réalisé | AJ3: Écart | AK3: Budget | AL3: Réalisé | AM3: Écart | AN3: Budget | AO3: Réalisé | AP3: Écart | AQ3: Budget | AR3: Réalisé | AS3: Écart
C4: Trésorerie début de mois | K4: =RÉALISÉ!D4 | N4: =RÉALISÉ!E4 | Q4: =RÉALISÉ!F4 | T4: =RÉALISÉ!G4
C5: ENTRÉES | D5: =BUDGET!D5+BUDGET!E5+BUDGET!F5+BUDGET!G5+BUDGET!H5+BUDGET!I5+BUDGET!J5+BUDGET!K5+BUDGET!L5+BUDGET!M5+BUDGET!N5+BUDGET!O5 | E5: =RÉALISÉ!D5+RÉALISÉ!E5+RÉALISÉ!F5+RÉALISÉ!G5+RÉALISÉ!H5+RÉALISÉ!I5+RÉALISÉ!J5+RÉALISÉ!K5+RÉALISÉ!L5+RÉALISÉ!M5+RÉALISÉ!N5+RÉALISÉ!O5 | G5: =D5-E5 | H5: =IF(D5<>0,E5/D5,"") | J5: =BUDGET!D5 | K5: =RÉALISÉ!D5 | L5: =K5-J5 | M5: =BUDGET!E5 | N5: =RÉALISÉ!E5 | O5: =N5-M5 | P5: =BUDGET!F5 | Q5: =RÉALISÉ!F5 | R5: =Q5-P5 | S5: =BUDGET!G5 | T5: =RÉALISÉ!G5 | U5: =T5-S5 | V5: =BUDGET!H5 | W5: =RÉALISÉ!H5 | X5: =W5-V5 | Y5: =BUDGET!I5 | Z5: =RÉALISÉ!I5 | AA5: =Z5-Y5 | AB5: =BUDGET!J5 | AC5: =RÉALISÉ!J5 | AD5: =AC5-AB5 | AE5: =BUDGET!K5 | AF5: =RÉALISÉ!K5 | AG5: =AF5-AE5 | AH5: =BUDGET!L5 | AI5: =RÉALISÉ!L5 | AJ5: =AI5-AH5 | AK5: =BUDGET!M5 | AL5: =RÉALISÉ!M5 | AM5: =AL5-AK5 | AN5: =BUDGET!N5 | AO5: =RÉALISÉ!N5 | AP5: =AO5-AN5 | AQ5: =BUDGET!O5 | AR5: =RÉALISÉ!O5 | AS5: =AR5-AQ5
C6: Recette de la billetterie | D6: =BUDGET!D6+BUDGET!E6+BUDGET!F6+BUDGET!G6+BUDGET!H6+BUDGET!I6+BUDGET!J6+BUDGET!K6+BUDGET!L6+BUDGET!M6+BUDGET!N6+BUDGET!O6 | E6: =RÉALISÉ!D6+RÉALISÉ!E6+RÉALISÉ!F6+RÉALISÉ!G6+RÉALISÉ!H6+RÉALISÉ!I6+RÉALISÉ!J6+RÉALISÉ!K6+RÉALISÉ!L6+RÉALISÉ!M6+RÉALISÉ!N6+RÉALISÉ!O6 | G6: =D6-E6 | H6: =IF(D6<>0,E6/D6,"") | I6: =IF(D6=0,"—",IF(H6>=1.1,"🔴 Dépassé",IF(H6>=0.9,"🟠 Attention",IF(H6>=0.5,"🟢 OK","🔵 En cours")))) | J6: =BUDGET!D6 | K6: =RÉALISÉ!D6 | L6: =K6-J6 | M6: =BUDGET!E6 | N6: =RÉALISÉ!E6 | O6: =N6-M6 | P6: =BUDGET!F6 | Q6: =RÉALISÉ!F6 | R6: =Q6-P6 | S6: =BUDGET!G6 | T6: =RÉALISÉ!G6 | U6: =T6-S6 | V6: =BUDGET!H6 | W6: =RÉALISÉ!H6 | X6: =W6-V6 | Y6: =BUDGET!I6 | Z6: =RÉALISÉ!I6 | AA6: =Z6-Y6 | AB6: =BUDGET!J6 | AC6: =RÉALISÉ!J6 | AD6: =AC6-AB6 | AE6: =BUDGET!K6 | AF6: =RÉALISÉ!K6 | AG6: =AF6-AE6 | AH6: =BUDGET!L6 | AI6: =RÉALISÉ!L6 | AJ6: =AI6-AH6 | AK6: =BUDGET!M6 | AL6: =RÉALISÉ!M6 | AM6: =AL6-AK6 | AN6: =BUDGET!N6 | AO6: =RÉALISÉ!N6 | AP6: =AO6-AN6 | AQ6: =BUDGET!O6 | AR6: =RÉALISÉ!O6 | AS6: =AR6-AQ6
C7: Rétrocession Commission - Machines à café | D7: =BUDGET!D7+BUDGET!E7+BUDGET!F7+BUDGET!G7+BUDGET!H7+BUDGET!I7+BUDGET!J7+BUDGET!K7+BUDGET!L7+BUDGET!M7+BUDGET!N7+BUDGET!O7 | E7: =RÉALISÉ!D7+RÉALISÉ!E7+RÉALISÉ!F7+RÉALISÉ!G7+RÉALISÉ!H7+RÉALISÉ!I7+RÉALISÉ!J7+RÉALISÉ!K7+RÉALISÉ!L7+RÉALISÉ!M7+RÉALISÉ!N7+RÉALISÉ!O7 | G7: =D7-E7 | H7: =IF(D7<>0,E7/D7,"") | I7: =IF(D7=0,"—",IF(H7>=1.1,"🔴 Dépassé",IF(H7>=0.9,"🟠 Attention",IF(H7>=0.5,"🟢 OK","🔵 En cours")))) | J7: =BUDGET!D7 | K7: =RÉALISÉ!D7 | L7: =K7-J7 | M7: =BUDGET!E7 | N7: =RÉALISÉ!E7 | O7: =N7-M7 | P7: =BUDGET!F7 | Q7: =RÉALISÉ!F7 | R7: =Q7-P7 | S7: =BUDGET!G7 | T7: =RÉALISÉ!G7 | U7: =T7-S7 | V7: =BUDGET!H7 | W7: =RÉALISÉ!H7 | X7: =W7-V7 | Y7: =BUDGET!I7 | Z7: =RÉALISÉ!I7 | AA7: =Z7-Y7 | AB7: =BUDGET!J7 | AC7: =RÉALISÉ!J7 | AD7: =AC7-AB7 | AE7: =BUDGET!K7 | AF7: =RÉALISÉ!K7 | AG7: =AF7-AE7 | AH7: =BUDGET!L7 | AI7: =RÉALISÉ!L7 | AJ7: =AI7-AH7 | AK7: =BUDGET!M7 | AL7: =RÉALISÉ!M7 | AM7: =AL7-AK7 | AN7: =BUDGET!N7 | AO7: =RÉALISÉ!N7 | AP7: =AO7-AN7 | AQ7: =BUDGET!O7 | AR7: =RÉALISÉ!O7 | AS7: =AR7-AQ7
C8: Remboursements achats salariés | D8: =BUDGET!D8+BUDGET!E8+BUDGET!F8+BUDGET!G8+BUDGET!H8+BUDGET!I8+BUDGET!J8+BUDGET!K8+BUDGET!L8+BUDGET!M8+BUDGET!N8+BUDGET!O8 | E8: =RÉALISÉ!D8+RÉALISÉ!E8+RÉALISÉ!F8+RÉALISÉ!G8+RÉALISÉ!H8+RÉALISÉ!I8+RÉALISÉ!J8+RÉALISÉ!K8+RÉALISÉ!L8+RÉALISÉ!M8+RÉALISÉ!N8+RÉALISÉ!O8 | G8: =D8-E8 | H8: =IF(D8<>0,E8/D8,"") | I8: =IF(D8=0,"—",IF(H8>=1.1,"🔴 Dépassé",IF(H8>=0.9,"🟠 Attention",IF(H8>=0.5,"🟢 OK","🔵 En cours")))) | J8: =BUDGET!D8 | K8: =RÉALISÉ!D8 | L8: =K8-J8 | M8: =BUDGET!E8 | N8: =RÉALISÉ!E8 | O8: =N8-M8 | P8: =BUDGET!F8 | Q8: =RÉALISÉ!F8 | R8: =Q8-P8 | S8: =BUDGET!G8 | T8: =RÉALISÉ!G8 | U8: =T8-S8 | V8: =BUDGET!H8 | W8: =RÉALISÉ!H8 | X8: =W8-V8 | Y8: =BUDGET!I8 | Z8: =RÉALISÉ!I8 | AA8: =Z8-Y8 | AB8: =BUDGET!J8 | AC8: =RÉALISÉ!J8 | AD8: =AC8-AB8 | AE8: =BUDGET!K8 | AF8: =RÉALISÉ!K8 | AG8: =AF8-AE8 | AH8: =BUDGET!L8 | AI8: =RÉALISÉ!L8 | AJ8: =AI8-AH8 | AK8: =BUDGET!M8 | AL8: =RÉALISÉ!M8 | AM8: =AL8-AK8 | AN8: =BUDGET!N8 | AO8: =RÉALISÉ!N8 | AP8: =AO8-AN8 | AQ8: =BUDGET!O8 | AR8: =RÉALISÉ!O8 | AS8: =AR8-AQ8
C9: Entrées non catégorisées | D9: =BUDGET!D9+BUDGET!E9+BUDGET!F9+BUDGET!G9+BUDGET!H9+BUDGET!I9+BUDGET!J9+BUDGET!K9+BUDGET!L9+BUDGET!M9+BUDGET!N9+BUDGET!O9 | E9: =RÉALISÉ!D9+RÉALISÉ!E9+RÉALISÉ!F9+RÉALISÉ!G9+RÉALISÉ!H9+RÉALISÉ!I9+RÉALISÉ!J9+RÉALISÉ!K9+RÉALISÉ!L9+RÉALISÉ!M9+RÉALISÉ!N9+RÉALISÉ!O9 | G9: =D9-E9 | H9: =IF(D9<>0,E9/D9,"") | I9: =IF(D9=0,"—",IF(H9>=1.1,"🔴 Dépassé",IF(H9>=0.9,"🟠 Attention",IF(H9>=0.5,"🟢 OK","🔵 En cours")))) | J9: =BUDGET!D9 | K9: =RÉALISÉ!D9 | L9: =K9-J9 | M9: =BUDGET!E9 | N9: =RÉALISÉ!E9 | O9: =N9-M9 | P9: =BUDGET!F9 | Q9: =RÉALISÉ!F9 | R9: =Q9-P9 | S9: =BUDGET!G9 | T9: =RÉALISÉ!G9 | U9: =T9-S9 | V9: =BUDGET!H9 | W9: =RÉALISÉ!H9 | X9: =W9-V9 | Y9: =BUDGET!I9 | Z9: =RÉALISÉ!I9 | AA9: =Z9-Y9 | AB9: =BUDGET!J9 | AC9: =RÉALISÉ!J9 | AD9: =AC9-AB9 | AE9: =BUDGET!K9 | AF9: =RÉALISÉ!K9 | AG9: =AF9-AE9 | AH9: =BUDGET!L9 | AI9: =RÉALISÉ!L9 | AJ9: =AI9-AH9 | AK9: =BUDGET!M9 | AL9: =RÉALISÉ!M9 | AM9: =AL9-AK9 | AN9: =BUDGET!N9 | AO9: =RÉALISÉ!N9 | AP9: =AO9-AN9 | AQ9: =BUDGET!O9 | AR9: =RÉALISÉ!O9 | AS9: =AR9-AQ9
C10: Remboursement de TVA | D10: =BUDGET!D10+BUDGET!E10+BUDGET!F10+BUDGET!G10+BUDGET!H10+BUDGET!I10+BUDGET!J10+BUDGET!K10+BUDGET!L10+BUDGET!M10+BUDGET!N10+BUDGET!O10 | E10: =RÉALISÉ!D10+RÉALISÉ!E10+RÉALISÉ!F10+RÉALISÉ!G10+RÉALISÉ!H10+RÉALISÉ!I10+RÉALISÉ!J10+RÉALISÉ!K10+RÉALISÉ!L10+RÉALISÉ!M10+RÉALISÉ!N10+RÉALISÉ!O10 | G10: =D10-E10 | H10: =IF(D10<>0,E10/D10,"") | I10: =IF(D10=0,"—",IF(H10>=1.1,"🔴 Dépassé",IF(H10>=0.9,"🟠 Attention",IF(H10>=0.5,"🟢 OK","🔵 En cours")))) | J10: =BUDGET!D10 | K10: =RÉALISÉ!D10 | L10: =K10-J10 | M10: =BUDGET!E10 | N10: =RÉALISÉ!E10 | O10: =N10-M10 | P10: =BUDGET!F10 | Q10: =RÉALISÉ!F10 | R10: =Q10-P10 | S10: =BUDGET!G10 | T10: =RÉALISÉ!G10 | U10: =T10-S10 | V10: =BUDGET!H10 | W10: =RÉALISÉ!H10 | X10: =W10-V10 | Y10: =BUDGET!I10 | Z10: =RÉALISÉ!I10 | AA10: =Z10-Y10 | AB10: =BUDGET!J10 | AC10: =RÉALISÉ!J10 | AD10: =AC10-AB10 | AE10: =BUDGET!K10 | AF10: =RÉALISÉ!K10 | AG10: =AF10-AE10 | AH10: =BUDGET!L10 | AI10: =RÉALISÉ!L10 | AJ10: =AI10-AH10 | AK10: =BUDGET!M10 | AL10: =RÉALISÉ!M10 | AM10: =AL10-AK10 | AN10: =BUDGET!N10 | AO10: =RÉALISÉ!N10 | AP10: =AO10-AN10 | AQ10: =BUDGET!O10 | AR10: =RÉALISÉ!O10 | AS10: =AR10-AQ10
C11: SORTIES | D11: =BUDGET!D11+BUDGET!E11+BUDGET!F11+BUDGET!G11+BUDGET!H11+BUDGET!I11+BUDGET!J11+BUDGET!K11+BUDGET!L11+BUDGET!M11+BUDGET!N11+BUDGET!O11 | E11: =RÉALISÉ!D11+RÉALISÉ!E11+RÉALISÉ!F11+RÉALISÉ!G11+RÉALISÉ!H11+RÉALISÉ!I11+RÉALISÉ!J11+RÉALISÉ!K11+RÉALISÉ!L11+RÉALISÉ!M11+RÉALISÉ!N11+RÉALISÉ!O11 | G11: =D11-E11 | H11: =IF(D11<>0,E11/D11,"") | J11: =BUDGET!D11 | K11: =RÉALISÉ!D11 | L11: =K11-J11 | M11: =BUDGET!E11 | N11: =RÉALISÉ!E11 | O11: =N11-M11 | P11: =BUDGET!F11 | Q11: =RÉALISÉ!F11 | R11: =Q11-P11 | S11: =BUDGET!G11 | T11: =RÉALISÉ!G11 | U11: =T11-S11 | V11: =BUDGET!H11 | W11: =RÉALISÉ!H11 | X11: =W11-V11 | Y11: =BUDGET!I11 | Z11: =RÉALISÉ!I11 | AA11: =Z11-Y11 | AB11: =BUDGET!J11 | AC11: =RÉALISÉ!J11 | AD11: =AC11-AB11 | AE11: =BUDGET!K11 | AF11: =RÉALISÉ!K11 | AG11: =AF11-AE11 | AH11: =BUDGET!L11 | AI11: =RÉALISÉ!L11 | AJ11: =AI11-AH11 | AK11: =BUDGET!M11 | AL11: =RÉALISÉ!M11 | AM11: =AL11-AK11 | AN11: =BUDGET!N11 | AO11: =RÉALISÉ!N11 | AP11: =AO11-AN11 | AQ11: =BUDGET!O11 | AR11: =RÉALISÉ!O11 | AS11: =AR11-AQ11
C12: Achat Billets | D12: =BUDGET!D12+BUDGET!E12+BUDGET!F12+BUDGET!G12+BUDGET!H12+BUDGET!I12+BUDGET!J12+BUDGET!K12+BUDGET!L12+BUDGET!M12+BUDGET!N12+BUDGET!O12 | E12: =RÉALISÉ!D12+RÉALISÉ!E12+RÉALISÉ!F12+RÉALISÉ!G12+RÉALISÉ!H12+RÉALISÉ!I12+RÉALISÉ!J12+RÉALISÉ!K12+RÉALISÉ!L12+RÉALISÉ!M12+RÉALISÉ!N12+RÉALISÉ!O12 | G12: =D12-E12 | H12: =IF(D12<>0,E12/D12,"") | I12: =IF(D12=0,"—",IF(H12>=1.1,"🔴 Dépassé",IF(H12>=0.9,"🟠 Attention",IF(H12>=0.5,"🟢 OK","🔵 En cours")))) | J12: =BUDGET!D12 | K12: =RÉALISÉ!D12 | L12: =K12-J12 | M12: =BUDGET!E12 | N12: =RÉALISÉ!E12 | O12: =N12-M12 | P12: =BUDGET!F12 | Q12: =RÉALISÉ!F12 | R12: =Q12-P12 | S12: =BUDGET!G12 | T12: =RÉALISÉ!G12 | U12: =T12-S12 | V12: =BUDGET!H12 | W12: =RÉALISÉ!H12 | X12: =W12-V12 | Y12: =BUDGET!I12 | Z12: =RÉALISÉ!I12 | AA12: =Z12-Y12 | AB12: =BUDGET!J12 | AC12: =RÉALISÉ!J12 | AD12: =AC12-AB12 | AE12: =BUDGET!K12 | AF12: =RÉALISÉ!K12 | AG12: =AF12-AE12 | AH12: =BUDGET!L12 | AI12: =RÉALISÉ!L12 | AJ12: =AI12-AH12 | AK12: =BUDGET!M12 | AL12: =RÉALISÉ!M12 | AM12: =AL12-AK12 | AN12: =BUDGET!N12 | AO12: =RÉALISÉ!N12 | AP12: =AO12-AN12 | AQ12: =BUDGET!O12 | AR12: =RÉALISÉ!O12 | AS12: =AR12-AQ12
C13: Europapark & Rulantica | D13: =BUDGET!D13+BUDGET!E13+BUDGET!F13+BUDGET!G13+BUDGET!H13+BUDGET!I13+BUDGET!J13+BUDGET!K13+BUDGET!L13+BUDGET!M13+BUDGET!N13+BUDGET!O13 | E13: =RÉALISÉ!D13+RÉALISÉ!E13+RÉALISÉ!F13+RÉALISÉ!G13+RÉALISÉ!H13+RÉALISÉ!I13+RÉALISÉ!J13+RÉALISÉ!K13+RÉALISÉ!L13+RÉALISÉ!M13+RÉALISÉ!N13+RÉALISÉ!O13 | G13: =D13-E13 | H13: =IF(D13<>0,E13/D13,"") | I13: =IF(D13=0,"—",IF(H13>=1.1,"🔴 Dépassé",IF(H13>=0.9,"🟠 Attention",IF(H13>=0.5,"🟢 OK","🔵 En cours")))) | J13: =BUDGET!D13 | K13: =RÉALISÉ!D13 | L13: =K13-J13 | M13: =BUDGET!E13 | N13: =RÉALISÉ!E13 | O13: =N13-M13 | P13: =BUDGET!F13 | Q13: =RÉALISÉ!F13 | R13: =Q13-P13 | S13: =BUDGET!G13 | T13: =RÉALISÉ!G13 | U13: =T13-S13 | V13: =BUDGET!H13 | W13: =RÉALISÉ!H13 | X13: =W13-V13 | Y13: =BUDGET!I13 | Z13: =RÉALISÉ!I13 | AA13: =Z13-Y13 | AB13: =BUDGET!J13 | AC13: =RÉALISÉ!J13 | AD13: =AC13-AB13 | AE13: =BUDGET!K13 | AF13: =RÉALISÉ!K13 | AG13: =AF13-AE13 | AH13: =BUDGET!L13 | AI13: =RÉALISÉ!L13 | AJ13: =AI13-AH13 | AK13: =BUDGET!M13 | AL13: =RÉALISÉ!M13 | AM13: =AL13-AK13 | AN13: =BUDGET!N13 | AO13: =RÉALISÉ!N13 | AP13: =AO13-AN13 | AQ13: =BUDGET!O13 | AR13: =RÉALISÉ!O13 | AS13: =AR13-AQ13
C14: Speedpark | D14: =BUDGET!D14+BUDGET!E14+BUDGET!F14+BUDGET!G14+BUDGET!H14+BUDGET!I14+BUDGET!J14+BUDGET!K14+BUDGET!L14+BUDGET!M14+BUDGET!N14+BUDGET!O14 | E14: =RÉALISÉ!D14+RÉALISÉ!E14+RÉALISÉ!F14+RÉALISÉ!G14+RÉALISÉ!H14+RÉALISÉ!I14+RÉALISÉ!J14+RÉALISÉ!K14+RÉALISÉ!L14+RÉALISÉ!M14+RÉALISÉ!N14+RÉALISÉ!O14 | G14: =D14-E14 | H14: =IF(D14<>0,E14/D14,"") | I14: =IF(D14=0,"—",IF(H14>=1.1,"🔴 Dépassé",IF(H14>=0.9,"🟠 Attention",IF(H14>=0.5,"🟢 OK","🔵 En cours")))) | J14: =BUDGET!D14 | K14: =RÉALISÉ!D14 | L14: =K14-J14 | M14: =BUDGET!E14 | N14: =RÉALISÉ!E14 | O14: =N14-M14 | P14: =BUDGET!F14 | Q14: =RÉALISÉ!F14 | R14: =Q14-P14 | S14: =BUDGET!G14 | T14: =RÉALISÉ!G14 | U14: =T14-S14 | V14: =BUDGET!H14 | W14: =RÉALISÉ!H14 | X14: =W14-V14 | Y14: =BUDGET!I14 | Z14: =RÉALISÉ!I14 | AA14: =Z14-Y14 | AB14: =BUDGET!J14 | AC14: =RÉALISÉ!J14 | AD14: =AC14-AB14 | AE14: =BUDGET!K14 | AF14: =RÉALISÉ!K14 | AG14: =AF14-AE14 | AH14: =BUDGET!L14 | AI14: =RÉALISÉ!L14 | AJ14: =AI14-AH14 | AK14: =BUDGET!M14 | AL14: =RÉALISÉ!M14 | AM14: =AL14-AK14 | AN14: =BUDGET!N14 | AO14: =RÉALISÉ!N14 | AP14: =AO14-AN14 | AQ14: =BUDGET!O14 | AR14: =RÉALISÉ!O14 | AS14: =AR14-AQ14
C15: Saint-Croix | D15: =BUDGET!D15+BUDGET!E15+BUDGET!F15+BUDGET!G15+BUDGET!H15+BUDGET!I15+BUDGET!J15+BUDGET!K15+BUDGET!L15+BUDGET!M15+BUDGET!N15+BUDGET!O15 | E15: =RÉALISÉ!D15+RÉALISÉ!E15+RÉALISÉ!F15+RÉALISÉ!G15+RÉALISÉ!H15+RÉALISÉ!I15+RÉALISÉ!J15+RÉALISÉ!K15+RÉALISÉ!L15+RÉALISÉ!M15+RÉALISÉ!N15+RÉALISÉ!O15 | G15: =D15-E15 | H15: =IF(D15<>0,E15/D15,"") | I15: =IF(D15=0,"—",IF(H15>=1.1,"🔴 Dépassé",IF(H15>=0.9,"🟠 Attention",IF(H15>=0.5,"🟢 OK","🔵 En cours")))) | J15: =BUDGET!D15 | K15: =RÉALISÉ!D15 | L15: =K15-J15 | M15: =BUDGET!E15 | N15: =RÉALISÉ!E15 | O15: =N15-M15 | P15: =BUDGET!F15 | Q15: =RÉALISÉ!F15 | R15: =Q15-P15 | S15: =BUDGET!G15 | T15: =RÉALISÉ!G15 | U15: =T15-S15 | V15: =BUDGET!H15 | W15: =RÉALISÉ!H15 | X15: =W15-V15 | Y15: =BUDGET!I15 | Z15: =RÉALISÉ!I15 | AA15: =Z15-Y15 | AB15: =BUDGET!J15 | AC15: =RÉALISÉ!J15 | AD15: =AC15-AB15 | AE15: =BUDGET!K15 | AF15: =RÉALISÉ!K15 | AG15: =AF15-AE15 | AH15: =BUDGET!L15 | AI15: =RÉALISÉ!L15 | AJ15: =AI15-AH15 | AK15: =BUDGET!M15 | AL15: =RÉALISÉ!M15 | AM15: =AL15-AK15 | AN15: =BUDGET!N15 | AO15: =RÉALISÉ!N15 | AP15: =AO15-AN15 | AQ15: =BUDGET!O15 | AR15: =RÉALISÉ!O15 | AS15: =AR15-AQ15
C16: Piscines | D16: =BUDGET!D16+BUDGET!E16+BUDGET!F16+BUDGET!G16+BUDGET!H16+BUDGET!I16+BUDGET!J16+BUDGET!K16+BUDGET!L16+BUDGET!M16+BUDGET!N16+BUDGET!O16 | E16: =RÉALISÉ!D16+RÉALISÉ!E16+RÉALISÉ!F16+RÉALISÉ!G16+RÉALISÉ!H16+RÉALISÉ!I16+RÉALISÉ!J16+RÉALISÉ!K16+RÉALISÉ!L16+RÉALISÉ!M16+RÉALISÉ!N16+RÉALISÉ!O16 | G16: =D16-E16 | H16: =IF(D16<>0,E16/D16,"") | I16: =IF(D16=0,"—",IF(H16>=1.1,"🔴 Dépassé",IF(H16>=0.9,"🟠 Attention",IF(H16>=0.5,"🟢 OK","🔵 En cours")))) | J16: =BUDGET!D16 | K16: =RÉALISÉ!D16 | L16: =K16-J16 | M16: =BUDGET!E16 | N16: =RÉALISÉ!E16 | O16: =N16-M16 | P16: =BUDGET!F16 | Q16: =RÉALISÉ!F16 | R16: =Q16-P16 | S16: =BUDGET!G16 | T16: =RÉALISÉ!G16 | U16: =T16-S16 | V16: =BUDGET!H16 | W16: =RÉALISÉ!H16 | X16: =W16-V16 | Y16: =BUDGET!I16 | Z16: =RÉALISÉ!I16 | AA16: =Z16-Y16 | AB16: =BUDGET!J16 | AC16: =RÉALISÉ!J16 | AD16: =AC16-AB16 | AE16: =BUDGET!K16 | AF16: =RÉALISÉ!K16 | AG16: =AF16-AE16 | AH16: =BUDGET!L16 | AI16: =RÉALISÉ!L16 | AJ16: =AI16-AH16 | AK16: =BUDGET!M16 | AL16: =RÉALISÉ!M16 | AM16: =AL16-AK16 | AN16: =BUDGET!N16 | AO16: =RÉALISÉ!N16 | AP16: =AO16-AN16 | AQ16: =BUDGET!O16 | AR16: =RÉALISÉ!O16 | AS16: =AR16-AQ16
C17: Parc Amnéville | D17: =BUDGET!D17+BUDGET!E17+BUDGET!F17+BUDGET!G17+BUDGET!H17+BUDGET!I17+BUDGET!J17+BUDGET!K17+BUDGET!L17+BUDGET!M17+BUDGET!N17+BUDGET!O17 | E17: =RÉALISÉ!D17+RÉALISÉ!E17+RÉALISÉ!F17+RÉALISÉ!G17+RÉALISÉ!H17+RÉALISÉ!I17+RÉALISÉ!J17+RÉALISÉ!K17+RÉALISÉ!L17+RÉALISÉ!M17+RÉALISÉ!N17+RÉALISÉ!O17 | G17: =D17-E17 | H17: =IF(D17<>0,E17/D17,"") | I17: =IF(D17=0,"—",IF(H17>=1.1,"🔴 Dépassé",IF(H17>=0.9,"🟠 Attention",IF(H17>=0.5,"🟢 OK","🔵 En cours")))) | J17: =BUDGET!D17 | K17: =RÉALISÉ!D17 | L17: =K17-J17 | M17: =BUDGET!E17 | N17: =RÉALISÉ!E17 | O17: =N17-M17 | P17: =BUDGET!F17 | Q17: =RÉALISÉ!F17 | R17: =Q17-P17 | S17: =BUDGET!G17 | T17: =RÉALISÉ!G17 | U17: =T17-S17 | V17: =BUDGET!H17 | W17: =RÉALISÉ!H17 | X17: =W17-V17 | Y17: =BUDGET!I17 | Z17: =RÉALISÉ!I17 | AA17: =Z17-Y17 | AB17: =BUDGET!J17 | AC17: =RÉALISÉ!J17 | AD17: =AC17-AB17 | AE17: =BUDGET!K17 | AF17: =RÉALISÉ!K17 | AG17: =AF17-AE17 | AH17: =BUDGET!L17 | AI17: =RÉALISÉ!L17 | AJ17: =AI17-AH17 | AK17: =BUDGET!M17 | AL17: =RÉALISÉ!M17 | AM17: =AL17-AK17 | AN17: =BUDGET!N17 | AO17: =RÉALISÉ!N17 | AP17: =AO17-AN17 | AQ17: =BUDGET!O17 | AR17: =RÉALISÉ!O17 | AS17: =AR17-AQ17
C18: Parc le petit prince | D18: =BUDGET!D18+BUDGET!E18+BUDGET!F18+BUDGET!G18+BUDGET!H18+BUDGET!I18+BUDGET!J18+BUDGET!K18+BUDGET!L18+BUDGET!M18+BUDGET!N18+BUDGET!O18 | E18: =RÉALISÉ!D18+RÉALISÉ!E18+RÉALISÉ!F18+RÉALISÉ!G18+RÉALISÉ!H18+RÉALISÉ!I18+RÉALISÉ!J18+RÉALISÉ!K18+RÉALISÉ!L18+RÉALISÉ!M18+RÉALISÉ!N18+RÉALISÉ!O18 | G18: =D18-E18 | H18: =IF(D18<>0,E18/D18,"") | I18: =IF(D18=0,"—",IF(H18>=1.1,"🔴 Dépassé",IF(H18>=0.9,"🟠 Attention",IF(H18>=0.5,"🟢 OK","🔵 En cours")))) | J18: =BUDGET!D18 | K18: =RÉALISÉ!D18 | L18: =K18-J18 | M18: =BUDGET!E18 | N18: =RÉALISÉ!E18 | O18: =N18-M18 | P18: =BUDGET!F18 | Q18: =RÉALISÉ!F18 | R18: =Q18-P18 | S18: =BUDGET!G18 | T18: =RÉALISÉ!G18 | U18: =T18-S18 | V18: =BUDGET!H18 | W18: =RÉALISÉ!H18 | X18: =W18-V18 | Y18: =BUDGET!I18 | Z18: =RÉALISÉ!I18 | AA18: =Z18-Y18 | AB18: =BUDGET!J18 | AC18: =RÉALISÉ!J18 | AD18: =AC18-AB18 | AE18: =BUDGET!K18 | AF18: =RÉALISÉ!K18 | AG18: =AF18-AE18 | AH18: =BUDGET!L18 | AI18: =RÉALISÉ!L18 | AJ18: =AI18-AH18 | AK18: =BUDGET!M18 | AL18: =RÉALISÉ!M18 | AM18: =AL18-AK18 | AN18: =BUDGET!N18 | AO18: =RÉALISÉ!N18 | AP18: =AO18-AN18 | AQ18: =BUDGET!O18 | AR18: =RÉALISÉ!O18 | AS18: =AR18-AQ18
C19: Didiland | D19: =BUDGET!D19+BUDGET!E19+BUDGET!F19+BUDGET!G19+BUDGET!H19+BUDGET!I19+BUDGET!J19+BUDGET!K19+BUDGET!L19+BUDGET!M19+BUDGET!N19+BUDGET!O19 | E19: =RÉALISÉ!D19+RÉALISÉ!E19+RÉALISÉ!F19+RÉALISÉ!G19+RÉALISÉ!H19+RÉALISÉ!I19+RÉALISÉ!J19+RÉALISÉ!K19+RÉALISÉ!L19+RÉALISÉ!M19+RÉALISÉ!N19+RÉALISÉ!O19 | G19: =D19-E19 | H19: =IF(D19<>0,E19/D19,"") | I19: =IF(D19=0,"—",IF(H19>=1.1,"🔴 Dépassé",IF(H19>=0.9,"🟠 Attention",IF(H19>=0.5,"🟢 OK","🔵 En cours")))) | J19: =BUDGET!D19 | K19: =RÉALISÉ!D19 | L19: =K19-J19 | M19: =BUDGET!E19 | N19: =RÉALISÉ!E19 | O19: =N19-M19 | P19: =BUDGET!F19 | Q19: =RÉALISÉ!F19 | R19: =Q19-P19 | S19: =BUDGET!G19 | T19: =RÉALISÉ!G19 | U19: =T19-S19 | V19: =BUDGET!H19 | W19: =RÉALISÉ!H19 | X19: =W19-V19 | Y19: =BUDGET!I19 | Z19: =RÉALISÉ!I19 | AA19: =Z19-Y19 | AB19: =BUDGET!J19 | AC19: =RÉALISÉ!J19 | AD19: =AC19-AB19 | AE19: =BUDGET!K19 | AF19: =RÉALISÉ!K19 | AG19: =AF19-AE19 | AH19: =BUDGET!L19 | AI19: =RÉALISÉ!L19 | AJ19: =AI19-AH19 | AK19: =BUDGET!M19 | AL19: =RÉALISÉ!M19 | AM19: =AL19-AK19 | AN19: =BUDGET!N19 | AO19: =RÉALISÉ!N19 | AP19: =AO19-AN19 | AQ19: =BUDGET!O19 | AR19: =RÉALISÉ!O19 | AS19: =AR19-AQ19
C20: Parc Asterix | D20: =BUDGET!D20+BUDGET!E20+BUDGET!F20+BUDGET!G20+BUDGET!H20+BUDGET!I20+BUDGET!J20+BUDGET!K20+BUDGET!L20+BUDGET!M20+BUDGET!N20+BUDGET!O20 | E20: =RÉALISÉ!D20+RÉALISÉ!E20+RÉALISÉ!F20+RÉALISÉ!G20+RÉALISÉ!H20+RÉALISÉ!I20+RÉALISÉ!J20+RÉALISÉ!K20+RÉALISÉ!L20+RÉALISÉ!M20+RÉALISÉ!N20+RÉALISÉ!O20 | G20: =D20-E20 | H20: =IF(D20<>0,E20/D20,"") | I20: =IF(D20=0,"—",IF(H20>=1.1,"🔴 Dépassé",IF(H20>=0.9,"🟠 Attention",IF(H20>=0.5,"🟢 OK","🔵 En cours")))) | J20: =BUDGET!D20 | K20: =RÉALISÉ!D20 | L20: =K20-J20 | M20: =BUDGET!E20 | N20: =RÉALISÉ!E20 | O20: =N20-M20 | P20: =BUDGET!F20 | Q20: =RÉALISÉ!F20 | R20: =Q20-P20 | S20: =BUDGET!G20 | T20: =RÉALISÉ!G20 | U20: =T20-S20 | V20: =BUDGET!H20 | W20: =RÉALISÉ!H20 | X20: =W20-V20 | Y20: =BUDGET!I20 | Z20: =RÉALISÉ!I20 | AA20: =Z20-Y20 | AB20: =BUDGET!J20 | AC20: =RÉALISÉ!J20 | AD20: =AC20-AB20 | AE20: =BUDGET!K20 | AF20: =RÉALISÉ!K20 | AG20: =AF20-AE20 | AH20: =BUDGET!L20 | AI20: =RÉALISÉ!L20 | AJ20: =AI20-AH20 | AK20: =BUDGET!M20 | AL20: =RÉALISÉ!M20 | AM20: =AL20-AK20 | AN20: =BUDGET!N20 | AO20: =RÉALISÉ!N20 | AP20: =AO20-AN20 | AQ20: =BUDGET!O20 | AR20: =RÉALISÉ!O20 | AS20: =AR20-AQ20
C21: Cinémas | D21: =BUDGET!D21+BUDGET!E21+BUDGET!F21+BUDGET!G21+BUDGET!H21+BUDGET!I21+BUDGET!J21+BUDGET!K21+BUDGET!L21+BUDGET!M21+BUDGET!N21+BUDGET!O21 | E21: =RÉALISÉ!D21+RÉALISÉ!E21+RÉALISÉ!F21+RÉALISÉ!G21+RÉALISÉ!H21+RÉALISÉ!I21+RÉALISÉ!J21+RÉALISÉ!K21+RÉALISÉ!L21+RÉALISÉ!M21+RÉALISÉ!N21+RÉALISÉ!O21 | G21: =D21-E21 | H21: =IF(D21<>0,E21/D21,"") | I21: =IF(D21=0,"—",IF(H21>=1.1,"🔴 Dépassé",IF(H21>=0.9,"🟠 Attention",IF(H21>=0.5,"🟢 OK","🔵 En cours")))) | J21: =BUDGET!D21 | K21: =RÉALISÉ!D21 | L21: =K21-J21 | M21: =BUDGET!E21 | N21: =RÉALISÉ!E21 | O21: =N21-M21 | P21: =BUDGET!F21 | Q21: =RÉALISÉ!F21 | R21: =Q21-P21 | S21: =BUDGET!G21 | T21: =RÉALISÉ!G21 | U21: =T21-S21 | V21: =BUDGET!H21 | W21: =RÉALISÉ!H21 | X21: =W21-V21 | Y21: =BUDGET!I21 | Z21: =RÉALISÉ!I21 | AA21: =Z21-Y21 | AB21: =BUDGET!J21 | AC21: =RÉALISÉ!J21 | AD21: =AC21-AB21 | AE21: =BUDGET!K21 | AF21: =RÉALISÉ!K21 | AG21: =AF21-AE21 | AH21: =BUDGET!L21 | AI21: =RÉALISÉ!L21 | AJ21: =AI21-AH21 | AK21: =BUDGET!M21 | AL21: =RÉALISÉ!M21 | AM21: =AL21-AK21 | AN21: =BUDGET!N21 | AO21: =RÉALISÉ!N21 | AP21: =AO21-AN21 | AQ21: =BUDGET!O21 | AR21: =RÉALISÉ!O21 | AS21: =AR21-AQ21
C22: Wonderbox | D22: =BUDGET!D22+BUDGET!E22+BUDGET!F22+BUDGET!G22+BUDGET!H22+BUDGET!I22+BUDGET!J22+BUDGET!K22+BUDGET!L22+BUDGET!M22+BUDGET!N22+BUDGET!O22 | E22: =RÉALISÉ!D22+RÉALISÉ!E22+RÉALISÉ!F22+RÉALISÉ!G22+RÉALISÉ!H22+RÉALISÉ!I22+RÉALISÉ!J22+RÉALISÉ!K22+RÉALISÉ!L22+RÉALISÉ!M22+RÉALISÉ!N22+RÉALISÉ!O22 | G22: =D22-E22 | H22: =IF(D22<>0,E22/D22,"") | I22: =IF(D22=0,"—",IF(H22>=1.1,"🔴 Dépassé",IF(H22>=0.9,"🟠 Attention",IF(H22>=0.5,"🟢 OK","🔵 En cours")))) | J22: =BUDGET!D22 | K22: =RÉALISÉ!D22 | L22: =K22-J22 | M22: =BUDGET!E22 | N22: =RÉALISÉ!E22 | O22: =N22-M22 | P22: =BUDGET!F22 | Q22: =RÉALISÉ!F22 | R22: =Q22-P22 | S22: =BUDGET!G22 | T22: =RÉALISÉ!G22 | U22: =T22-S22 | V22: =BUDGET!H22 | W22: =RÉALISÉ!H22 | X22: =W22-V22 | Y22: =BUDGET!I22 | Z22: =RÉALISÉ!I22 | AA22: =Z22-Y22 | AB22: =BUDGET!J22 | AC22: =RÉALISÉ!J22 | AD22: =AC22-AB22 | AE22: =BUDGET!K22 | AF22: =RÉALISÉ!K22 | AG22: =AF22-AE22 | AH22: =BUDGET!L22 | AI22: =RÉALISÉ!L22 | AJ22: =AI22-AH22 | AK22: =BUDGET!M22 | AL22: =RÉALISÉ!M22 | AM22: =AL22-AK22 | AN22: =BUDGET!N22 | AO22: =RÉALISÉ!N22 | AP22: =AO22-AN22 | AQ22: =BUDGET!O22 | AR22: =RÉALISÉ!O22 | AS22: =AR22-AQ22
C23: Parc Fraispertuis | D23: =BUDGET!D23+BUDGET!E23+BUDGET!F23+BUDGET!G23+BUDGET!H23+BUDGET!I23+BUDGET!J23+BUDGET!K23+BUDGET!L23+BUDGET!M23+BUDGET!N23+BUDGET!O23 | E23: =RÉALISÉ!D23+RÉALISÉ!E23+RÉALISÉ!F23+RÉALISÉ!G23+RÉALISÉ!H23+RÉALISÉ!I23+RÉALISÉ!J23+RÉALISÉ!K23+RÉALISÉ!L23+RÉALISÉ!M23+RÉALISÉ!N23+RÉALISÉ!O23 | G23: =D23-E23 | H23: =IF(D23<>0,E23/D23,"") | I23: =IF(D23=0,"—",IF(H23>=1.1,"🔴 Dépassé",IF(H23>=0.9,"🟠 Attention",IF(H23>=0.5,"🟢 OK","🔵 En cours")))) | J23: =BUDGET!D23 | K23: =RÉALISÉ!D23 | L23: =K23-J23 | M23: =BUDGET!E23 | N23: =RÉALISÉ!E23 | O23: =N23-M23 | P23: =BUDGET!F23 | Q23: =RÉALISÉ!F23 | R23: =Q23-P23 | S23: =BUDGET!G23 | T23: =RÉALISÉ!G23 | U23: =T23-S23 | V23: =BUDGET!H23 | W23: =RÉALISÉ!H23 | X23: =W23-V23 | Y23: =BUDGET!I23 | Z23: =RÉALISÉ!I23 | AA23: =Z23-Y23 | AB23: =BUDGET!J23 | AC23: =RÉALISÉ!J23 | AD23: =AC23-AB23 | AE23: =BUDGET!K23 | AF23: =RÉALISÉ!K23 | AG23: =AF23-AE23 | AH23: =BUDGET!L23 | AI23: =RÉALISÉ!L23 | AJ23: =AI23-AH23 | AK23: =BUDGET!M23 | AL23: =RÉALISÉ!M23 | AM23: =AL23-AK23 | AN23: =BUDGET!N23 | AO23: =RÉALISÉ!N23 | AP23: =AO23-AN23 | AQ23: =BUDGET!O23 | AR23: =RÉALISÉ!O23 | AS23: =AR23-AQ23
... C59: Paiement TVA | D59: =BUDGET!D59+BUDGET!E59+BUDGET!F59+BUDGET!G59+BUDGET!H59+BUDGET!I59+BUDGET!J59+BUDGET!K59+BUDGET!L59+BUDGET!M59+BUDGET!N59+BUDGET!O59 | E59: =RÉALISÉ!D59+RÉALISÉ!E59+RÉALISÉ!F59+RÉALISÉ!G59+RÉALISÉ!H59+RÉALISÉ!I59+RÉALISÉ!J59+RÉALISÉ!K59+RÉALISÉ!L59+RÉALISÉ!M59+RÉALISÉ!N59+RÉALISÉ!O59 | G59: =D59-E59 | H59: =IF(D59<>0,E59/D59,"") | I59: =IF(D59=0,"—",IF(H59>=1.1,"🔴 Dépassé",IF(H59>=0.9,"🟠 Attention",IF(H59>=0.5,"🟢 OK","🔵 En cours")))) | J59: =BUDGET!D59 | K59: =RÉALISÉ!D59 | L59: =K59-J59 | M59: =BUDGET!E59 | N59: =RÉALISÉ!E59 | O59: =N59-M59 | P59: =BUDGET!F59 | Q59: =RÉALISÉ!F59 | R59: =Q59-P59 | S59: =BUDGET!G59 | T59: =RÉALISÉ!G59 | U59: =T59-S59 | V59: =BUDGET!H59 | W59: =RÉALISÉ!H59 | X59: =W59-V59 | Y59: =BUDGET!I59 | Z59: =RÉALISÉ!I59 | AA59: =Z59-Y59 | AB59: =BUDGET!J59 | AC59: =RÉALISÉ!J59 | AD59: =AC59-AB59 | AE59: =BUDGET!K59 | AF59: =RÉALISÉ!K59 | AG59: =AF59-AE59 | AH59: =BUDGET!L59 | AI59: =RÉALISÉ!L59 | AJ59: =AI59-AH59 | AK59: =BUDGET!M59 | AL59: =RÉALISÉ!M59 | AM59: =AL59-AK59 | AN59: =BUDGET!N59 | AO59: =RÉALISÉ!N59 | AP59: =AO59-AN59 | AQ59: =BUDGET!O59 | AR59: =RÉALISÉ!O59 | AS59: =AR59-AQ59
C60: Trésorerie fin de mois | K60: =RÉALISÉ!D60 | N60: =RÉALISÉ!E60 | Q60: =RÉALISÉ!F60 | T60: =RÉALISÉ!G60

Sheet BUDGET
C1: 💰 BUDGET ANNUEL — Saisie par catégorie et par mois | CSE LIDL ENTZHEIM
C2: Saisir le budget prévisionnel par catégorie (cellules bleues). Exercice : Mars 2026 – Février 2027.
C3: CATÉGORIE | D3: Mars 2026 | E3: Avril 2026 | F3: Mai 2026 | G3: Juin 2026 | H3: Juillet 2026 | I3: Août 2026 | J3: Septembre 2026 | K3: Octobre 2026 | L3: Novembre 2026 | M3: Décembre 2026 | N3: Janvier 2027 | O3: Février 2027 | P3: TOTAL BUDGET
C4: Trésorerie début de mois
C5: ENTRÉES
C6: Recette de la billetterie | D6: 13000 | E6: 0 | F6: 0 | G6: 0 | H6: 0 | I6: 0 | J6: 0 | K6: 0 | L6: 0 | M6: 0 | N6: 0 | O6: 0 | P6: =SUM(D6:O6)
C7: Rétrocession Commission - Machines à café | D7: 0 | E7: 0 | F7: 0 | G7: 0 | H7: 0 | I7: 0 | J7: 0 | K7: 0 | L7: 0 | M7: 0 | N7: 0 | O7: 0 | P7: =SUM(D7:O7)
C8: Remboursements achats salariés | D8: 0 | E8: 0 | F8: 0 | G8: 0 | H8: 0 | I8: 0 | J8: 0 | K8: 0 | L8: 0 | M8: 0 | N8: 0 | O8: 0 | P8: =SUM(D8:O8)
C9: Entrées non catégorisées | D9: 0 | E9: 0 | F9: 0 | G9: 0 | H9: 0 | I9: 0 | J9: 0 | K9: 0 | L9: 0 | M9: 0 | N9: 0 | O9: 0 | P9: =SUM(D9:O9)
C10: Remboursement de TVA | D10: 0 | E10: 0 | F10: 0 | G10: 0 | H10: 0 | I10: 0 | J10: 0 | K10: 0 | L10: 0 | M10: 0 | N10: 0 | O10: 0 | P10: =SUM(D10:O10)
C11: SORTIES
C12: Achat Billets | D12: 0 | E12: 0 | F12: 0 | G12: 0 | H12: 0 | I12: 0 | J12: 0 | K12: 0 | L12: 0 | M12: 0 | N12: 0 | O12: 0 | P12: =SUM(D12:O12)
C13: Europapark & Rulantica | D13: 0 | E13: 0 | F13: 0 | G13: 0 | H13: 0 | I13: 0 | J13: 0 | K13: 0 | L13: 0 | M13: 0 | N13: 0 | O13: 0 | P13: =SUM(D13:O13)
C14: Speedpark | D14: 0 | E14: 0 | F14: 0 | G14: 0 | H14: 0 | I14: 0 | J14: 0 | K14: 0 | L14: 0 | M14: 0 | N14: 0 | O14: 0 | P14: =SUM(D14:O14)
C15: Saint-Croix | D15: 0 | E15: 0 | F15: 0 | G15: 0 | H15: 0 | I15: 0 | J15: 0 | K15: 0 | L15: 0 | M15: 0 | N15: 0 | O15: 0 | P15: =SUM(D15:O15)
C16: Piscines | D16: 0 | E16: 0 | F16: 0 | G16: 0 | H16: 0 | I16: 0 | J16: 0 | K16: 0 | L16: 0 | M16: 0 | N16: 0 | O16: 0 | P16: =SUM(D16:O16)
C17: Parc Amnéville | D17: 0 | E17: 0 | F17: 0 | G17: 0 | H17: 0 | I17: 0 | J17: 0 | K17: 0 | L17: 0 | M17: 0 | N17: 0 | O17: 0 | P17: =SUM(D17:O17)
C18: Parc le petit prince | D18: 0 | E18: 0 | F18: 0 | G18: 0 | H18: 0 | I18: 0 | J18: 0 | K18: 0 | L18: 0 | M18: 0 | N18: 0 | O18: 0 | P18: =SUM(D18:O18)
C19: Didiland | D19: 0 | E19: 0 | F19: 0 | G19: 0 | H19: 0 | I19: 0 | J19: 0 | K19: 0 | L19: 0 | M19: 0 | N19: 0 | O19: 0 | P19: =SUM(D19:O19)
C20: Parc Asterix | D20: 0 | E20: 0 | F20: 0 | G20: 0 | H20: 0 | I20: 0 | J20: 0 | K20: 0 | L20: 0 | M20: 0 | N20: 0 | O20: 0 | P20: =SUM(D20:O20)
C21: Cinémas | D21: 0 | E21: 0 | F21: 0 | G21: 0 | H21: 0 | I21: 0 | J21: 0 | K21: 0 | L21: 0 | M21: 0 | N21: 0 | O21: 0 | P21: =SUM(D21:O21)
C22: Wonderbox | D22: 0 | E22: 0 | F22: 0 | G22: 0 | H22: 0 | I22: 0 | J22: 0 | K22: 0 | L22: 0 | M22: 0 | N22: 0 | O22: 0 | P22: =SUM(D22:O22)
C23: Parc Fraispertuis | D23: 0 | E23: 0 | F23: 0 | G23: 0 | H23: 0 | I23: 0 | J23: 0 | K23: 0 | L23: 0 | M23: 0 | N23: 0 | O23: 0 | P23: =SUM(D23:O23)
... C59: Paiement TVA | D59: 0 | E59: 0 | F59: 0 | G59: 0 | H59: 0 | I59: 0 | J59: 0 | K59: 0 | L59: 0 | M59: 0 | N59: 0 | O59: 0 | P59: =SUM(D59:O59)
C60: Trésorerie fin de mois
C62: 🔵 Cellules bleues = budget à saisir | 🟡 Cellules jaunes = budget pré-rempli depuis Pennylane

Sheet RÉALISÉ
C1: 📥 DONNÉES RÉALISÉES — Import Pennylane | CSE LIDL ENTZHEIM
C2: Mettre à jour ce tableau chaque mois depuis Pennylane (Plan de trésorerie > onglet Réalisé)
C3: CATÉGORIE | D3: Mars 2026 | E3: Avril 2026 | F3: Mai 2026 | G3: Juin 2026 | H3: Juillet 2026 | I3: Août 2026 | J3: Septembre 2026 | K3: Octobre 2026 | L3: Novembre 2026 | M3: Décembre 2026 | N3: Janvier 2027 | O3: Février 2027 | P3: TOTAL
C4: Trésorerie début de mois | D4: 518635.71 | E4: 506826.28 | F4: 514364.64 | G4: 470450.89 | P4: =SUM(D4:O4)
C5: ENTRÉES | D5: 0 | E5: 212.53 | F5: 1185.38 | G5: 110 | P5: =SUM(D5:O5)
C6: Recette de la billetterie | D6: 0 | E6: 0 | F6: 0 | G6: 0 | H6: 0 | I6: 0 | J6: 0 | K6: 0 | L6: 0 | M6: 0 | N6: 0 | O6: 0 | P6: =SUM(D6:O6)
C7: Rétrocession Commission - Machines à café | D7: 0 | E7: 0 | F7: 0 | G7: 0 | H7: 0 | I7: 0 | J7: 0 | K7: 0 | L7: 0 | M7: 0 | N7: 0 | O7: 0 | P7: =SUM(D7:O7)
C8: Remboursements achats salariés | D8: 0 | E8: 0 | F8: 0 | G8: 0 | H8: 0 | I8: 0 | J8: 0 | K8: 0 | L8: 0 | M8: 0 | N8: 0 | O8: 0 | P8: =SUM(D8:O8)
C9: Entrées non catégorisées | D9: 0 | E9: 212.53 | F9: 1185.38 | G9: 110 | H9: 0 | I9: 0 | J9: 0 | K9: 0 | L9: 0 | M9: 0 | N9: 0 | O9: 0 | P9: =SUM(D9:O9)
C10: Remboursement de TVA | D10: 0 | E10: 0 | F10: 0 | G10: 0 | H10: 0 | I10: 0 | J10: 0 | K10: 0 | L10: 0 | M10: 0 | N10: 0 | O10: 0 | P10: =SUM(D10:O10)
C11: SORTIES | D11: 11809.43 | E11: 33744.49 | F11: 4028.81 | G11: -1144.54 | P11: =SUM(D11:O11)
C12: Achat Billets | D12: -1797.98 | E12: -19859.22 | F12: -4255.27 | G12: -5426.49 | H12: 0 | I12: 0 | J12: 0 | K12: 0 | L12: 0 | M12: 0 | N12: 0 | O12: 0 | P12: =SUM(D12:O12)
C13: Europapark & Rulantica | D13: 0 | E13: 0 | F13: 0 | G13: 0 | H13: 0 | I13: 0 | J13: 0 | K13: 0 | L13: 0 | M13: 0 | N13: 0 | O13: 0 | P13: =SUM(D13:O13)
C14: Speedpark | D14: 0 | E14: 0 | F14: 0 | G14: 0 | H14: 0 | I14: 0 | J14: 0 | K14: 0 | L14: 0 | M14: 0 | N14: 0 | O14: 0 | P14: =SUM(D14:O14)
C15: Saint-Croix | D15: 0 | E15: 0 | F15: 0 | G15: 0 | H15: 0 | I15: 0 | J15: 0 | K15: 0 | L15: 0 | M15: 0 | N15: 0 | O15: 0 | P15: =SUM(D15:O15)
C16: Piscines | D16: 0 | E16: 0 | F16: 0 | G16: 0 | H16: 0 | I16: 0 | J16: 0 | K16: 0 | L16: 0 | M16: 0 | N16: 0 | O16: 0 | P16: =SUM(D16:O16)
C17: Parc Amnéville | D17: 0 | E17: 0 | F17: 0 | G17: 0 | H17: 0 | I17: 0 | J17: 0 | K17: 0 | L17: 0 | M17: 0 | N17: 0 | O17: 0 | P17: =SUM(D17:O17)
C18: Parc le petit prince | D18: 0 | E18: 0 | F18: 0 | G18: 0 | H18: 0 | I18: 0 | J18: 0 | K18: 0 | L18: 0 | M18: 0 | N18: 0 | O18: 0 | P18: =SUM(D18:O18)
C19: Didiland | D19: 0 | E19: 0 | F19: 0 | G19: 0 | H19: 0 | I19: 0 | J19: 0 | K19: 0 | L19: 0 | M19: 0 | N19: 0 | O19: 0 | P19: =SUM(D19:O19)
C20: Parc Asterix | D20: 0 | E20: 0 | F20: 0 | G20: 0 | H20: 0 | I20: 0 | J20: 0 | K20: 0 | L20: 0 | M20: 0 | N20: 0 | O20: 0 | P20: =SUM(D20:O20)
C21: Cinémas | D21: 0 | E21: 0 | F21: 0 | G21: 0 | H21: 0 | I21: 0 | J21: 0 | K21: 0 | L21: 0 | M21: 0 | N21: 0 | O21: 0 | P21: =SUM(D21:O21)
C22: Wonderbox | D22: 0 | E22: 0 | F22: 0 | G22: 0 | H22: 0 | I22: 0 | J22: 0 | K22: 0 | L22: 0 | M22: 0 | N22: 0 | O22: 0 | P22: =SUM(D22:O22)
C23: Parc Fraispertuis | D23: 0 | E23: 0 | F23: 0 | G23: 0 | H23: 0 | I23: 0 | J23: 0 | K23: 0 | L23: 0 | M23: 0 | N23: 0 | O23: 0 | P23: =SUM(D23:O23)
... C59: Paiement TVA | D59: 0 | E59: 0 | F59: 0 | G59: 0 | H59: 0 | I59: 0 | J59: 0 | K59: 0 | L59: 0 | M59: 0 | N59: 0 | O59: 0 | P59: =SUM(D59:O59)
C60: Trésorerie fin de mois | D60: 506826.28 | E60: 514364.64 | F60: 470450.89 | P60: =SUM(D60:O60)
C62: 🔵 Cellules bleues = données Pennylane saisies | Mettre à jour mois par mois

Sheet ALERTES
B1: ⚠️ TABLEAU DES ALERTES AUTOMATIQUES | CSE LIDL ENTZHEIM
B2: Alertes calculées dynamiquement à partir du Plan de Trésorerie. Mis à jour à chaque modification des onglets BUDGET et RÉALISÉ.
B3: # | C3: NIVEAU | D3: CATÉGORIE | E3: BUDGET N | F3: RÉALISÉ | G3: ÉCART € | H3: ALERTE
B4: 1 | C4: 🔴 CRITIQUE | D4: Sorties non catégorisées | E4: ='PLAN TRÉSO'!D58 | F4: ='PLAN TRÉSO'!E58 | G4: ='PLAN TRÉSO'!E58-'PLAN TRÉSO'!D58 | H4: Solde très élevé — ventiler les écritures dans Pennylane
B5: 2 | C5: 🟡 ATTENTION | D5: Achat Billets | E5: ='PLAN TRÉSO'!D12 | F5: ='PLAN TRÉSO'!E12 | G5: ='PLAN TRÉSO'!E12-'PLAN TRÉSO'!D12 | H5: Vérifier que les remboursements/avances sont corrects
B6: 3 | C6: 🔵 INFO | D6: SORTIES | E6: ='PLAN TRÉSO'!D11 | F6: ='PLAN TRÉSO'!E11 | G6: ='PLAN TRÉSO'!E11-'PLAN TRÉSO'!D11 | H6: Suivi global des dépenses — budget à saisir
B7: 4 | C7: 🔵 INFO | D7: ENTRÉES | E7: ='PLAN TRÉSO'!D5 | F7: ='PLAN TRÉSO'!E5 | G7: ='PLAN TRÉSO'!E5-'PLAN TRÉSO'!D5 | H7: Suivi global des recettes — budget à saisir
B8: 5 | C8: 🟢 OK | D8: Activités de loisirs | E8: ='PLAN TRÉSO'!D29 | F8: ='PLAN TRÉSO'!E29 | G8: ='PLAN TRÉSO'!E29-'PLAN TRÉSO'!D29 | H8: Niveau de dépenses normal pour la saison
B9: 6 | C9: 🟢 OK | D9: Frais bancaires | E9: ='PLAN TRÉSO'!D42 | F9: ='PLAN TRÉSO'!E42 | G9: ='PLAN TRÉSO'!E42-'PLAN TRÉSO'!D42 | H9: Frais dans la norme pour un CSE PME
B10: 7 | C10: 🟢 OK | D10: Téléphone & Internet | E10: ='PLAN TRÉSO'!D54 | F10: ='PLAN TRÉSO'!E54 | G10: ='PLAN TRÉSO'!E54-'PLAN TRÉSO'!D54 | H10: Abonnement régulier — comparer au budget N-1
B11: 8 | C11: 🔵 INFO | D11: Aides aux voyages | E11: ='PLAN TRÉSO'!D31 | F11: ='PLAN TRÉSO'!E31 | G11: ='PLAN TRÉSO'!E31-'PLAN TRÉSO'!D31 | H11: Budget décembre 2026 prévu : 12 000 € (Pennylane)
B14: 📌 COMMENT RÉDUIRE LES ALERTES
B15: 1. Renseignez le BUDGET annuel dans l'onglet BUDGET (colonne par mois)
B16: 2. Mettez à jour les données dans l'onglet RÉALISÉ après chaque export Pennylane
B17: 3. Vérifiez les écritures "non catégorisées" dans Pennylane et affectez-les aux bons codes analytiques
B18: 4. Pour les alertes 🔴 CRITIQUE : action immédiate requise du trésorier

Sheet MODE D'EMPLOI
B1: 📖 MODE D'EMPLOI — COCKPIT CSE LIDL ENTZHEIM
B3: 🎯 OBJECTIF DE L'OUTIL
B4: ▸ | C4: Cet outil de pilotage de trésorerie est conçu pour le CSE LIDL ENTZHEIM.
B5: ▸ | C5: Il permet de suivre en temps réel le budget vs réalisé par catégorie analytique,
B6: ▸ | C6: d'anticiper les dépassements et d'alimenter les réunions de commission économique.
B8: 📥 MISE À JOUR MENSUELLE (Workflow)
B9: ▸ | C9: 1. Connectez-vous à Pennylane | D9: pennylane.com
B10: ▸ | C10: 2. Allez dans Gestion > Plan de trésorerie | D10: Sélectionner la période exercice
B11: ▸ | C11: 3. Exportez l'onglet "Réalisé" (filtre : mois clos) | D11: Format Excel ou CSV
B12: ▸ | C12: 4. Copiez les valeurs dans l'onglet RÉALISÉ | D12: ⚠ Coller valeurs uniquement (Ctrl+Maj+V)
B13: ▸ | C13: 5. Vérifiez que les catégories correspondent | D13: Si nouveau code analytique : ajouter une ligne
B14: ▸ | C14: 6. Consultez le COCKPIT pour le résumé | D14: Tableau auto-actualisé
B16: 💰 SAISIE DU BUDGET
B17: ▸ | C17: Ouvrir l'onglet BUDGET | D17: Cellules bleues = à saisir
B18: ▸ | C18: Saisir le budget mensuel pour chaque catégorie | D18: Valeurs en euros HT
B19: ▸ | C19: Les totaux annuels se calculent automatiquement | D19: Colonne "Total Budget" à droite
B20: ▸ | C20: Répéter chaque exercice (copier-coller le fichier | D20: Adapter les mois dans la ligne 3
B22: 📊 LECTURE DU COCKPIT
B23: ▸ | C23: 🟢 OK : Réalisé < 90% du budget → dans les clous
B24: ▸ | C24: 🟠 Attention : Réalisé entre 90% et 110% du budget | D24: Surveiller le mois suivant
B25: ▸ | C25: 🔴 Dépassé : Réalisé > 110% du budget | D25: Action requise : régularisation ou révision
B26: ▸ | C26: 🔵 En cours : Budget > 0 mais peu consommé | D26: Normal en début d'exercice
B27: ▸ | C27: — : Pas de budget saisi pour cette catégorie | D27: Compléter l'onglet BUDGET
B29: ⚠️ POINTS D'ATTENTION
B30: ▸ | C30: "Sorties non catégorisées" élevées : 59 097 € sur 4 mois | D30: Ventiler dans Pennylane
B31: ▸ | C31: "Achat Billets" en négatif : remboursements > achats | D31: Vérifier le solde net
B32: ▸ | C32: Budget Pennylane quasi-vide : saisir le budget dans l'onglet BUDGET
B33: ▸ | C33: Trésorerie stable à 470 455 € depuis Juin → pas de risque court terme
B35: 🔄 MISE À JOUR DE L'OUTIL
B36: ▸ | C36: Renommer le fichier avec la date : COCKPIT_CSE_YYYY_MM.xlsx
B37: ▸ | C37: Archiver la version précédente dans un dossier /Archives/
B38: ▸ | C38: En fin d'exercice (Fév 2027) : dupliquer et créer le budget N+1
